hou_garden/__init__.py
hou_garden/agent_build/.gitignore
hou_garden/agent_build/__init__.py
hou_garden/agent_build/use_config_build_agent_app.py
hou_garden/agents/__init__.py
hou_garden/agents/hou_agent/.gitignore
hou_garden/agents/hou_agent/__init__.py
hou_garden/agents/hou_agent/agent_demo.py
hou_garden/agents/planner/.gitignore
hou_garden/agents/planner/__init__.py
hou_garden/agents/planner/agent.py
hou_garden/agents/property_search/__init__.py
hou_garden/agents/property_search/agent.py
hou_garden/agents/tools/.gitignore
hou_garden/agents/tools/__init__.py
hou_garden/agents/tools/query_hougarden_info.py
hou_garden/agents/user_profiling/.gitignore
hou_garden/agents/user_profiling/__init__.py
hou_garden/agents/user_profiling/agent.py
hou_garden/agents/user_profiling/response_template.py
hou_garden/apps/.gitignore
hou_garden/apps/__init__.py
hou_garden/apps/hougarden_cli.py
hou_garden/apps/hougarden_finder.py
hou_garden/apps/hougarden_finder_client.py
hou_garden/ask_hougarn_dify/.gitignore
hou_garden/ask_hougarn_dify/__init__.py
hou_garden/ask_hougarn_dify/main.py
hou_garden/ask_hougarn_dify/交付问题反馈报告.md
hou_garden/ask_hougarn_dify/交接案例 01.md
hou_garden/ask_hougarn_dify/交接案例 02.md
hou_garden/ask_hougarn_dify/问题案例和目的.md
hou_garden/configs/config.yaml
hou_garden/configs/agents/planner.yaml
hou_garden/configs/agents/property_search.yaml
hou_garden/configs/agents/user_profiling.yaml
hou_garden/configs/agents_old/planner.yaml
hou_garden/configs/agents_old/property_search.yaml
hou_garden/configs/agents_old/user_profiling.yaml
hou_garden/configs/apps/ask-hougarden.yaml
hou_garden/configs/apps/hougarden-finder.yaml
hou_garden/configs/embedders/default.yaml
hou_garden/configs/envs/default.yaml
hou_garden/configs/knowledge/default.yaml
hou_garden/configs/memorys/sqlite.yaml
hou_garden/configs/models/deepseek.yaml
hou_garden/configs/models/openai.yaml
hou_garden/configs/storage/default.yaml
hou_garden/configs/storages/default.yaml
hou_garden/configs/tools/default.yaml
hou_garden-0.0.8.dist-info/licenses/LICENSE
hou_garden-0.0.8.dist-info/METADATA
hou_garden-0.0.8.dist-info/WHEEL
hou_garden-0.0.8.dist-info/entry_points.txt
hou_garden-0.0.8.dist-info/top_level.txt
hou_garden-0.0.8.dist-info/RECORD
