Metadata-Version: 2.4
Name: hou-garden
Version: 0.0.8
Author: Cheng Chen
Author-email: cheng.chen@hougarden.com
Classifier: Development Status :: 2 - Pre-Alpha
Classifier: Intended Audience :: Developers
Classifier: Natural Language :: English
Classifier: Programming Language :: Python :: 3.10
Requires-Python: >=3.10
License-File: LICENSE
Requires-Dist: sphinx==8.1.3
Requires-Dist: sphinx-rtd-theme==3.0.2
Requires-Dist: pytest==8.3.5
Requires-Dist: pytest-cov==6.0.0
Requires-Dist: pyrootutils==1.0.4
Requires-Dist: pre-commit==4.1.0
Requires-Dist: twine==6.1.0
Requires-Dist: wheel>=0.45.1
Requires-Dist: coverage==7.6.12
Requires-Dist: furo==2024.8.6
Requires-Dist: myst-parser==4.0.1
Requires-Dist: pytest-mock==3.14.0
Requires-Dist: pendulum
Requires-Dist: python-dotenv==1.0.1
Requires-Dist: cookiecutter
Requires-Dist: setuptools
Requires-Dist: click
Requires-Dist: openpyxl==3.1.5
Requires-Dist: attrs<26,>=25.1.0
Requires-Dist: pathlib
Requires-Dist: ray
Requires-Dist: ray[serve]
Requires-Dist: instructor
Requires-Dist: agno
Requires-Dist: openai
Requires-Dist: numpy==1.26.4
Requires-Dist: pandas
Requires-Dist: python-docx==1.1.2
Requires-Dist: python-magic==0.4.27
Requires-Dist: markdown==3.7
Requires-Dist: pyyaml
Requires-Dist: toml
Requires-Dist: mcp
Requires-Dist: fastapi
Requires-Dist: fastmcp
Requires-Dist: chromadb
Requires-Dist: pylance
Requires-Dist: lancedb
Requires-Dist: tantivy
Requires-Dist: sqlalchemy
Requires-Dist: duckdb
Requires-Dist: psycopg2-binary
Requires-Dist: googlesearch-python
Requires-Dist: pycountry
Requires-Dist: ddgs
Requires-Dist: hydra-core
Requires-Dist: requests
Dynamic: author
Dynamic: author-email
Dynamic: classifier
Dynamic: description
Dynamic: description-content-type
Dynamic: license-file
Dynamic: requires-dist
Dynamic: requires-python
